Workbook
Name aporte_inicial: Simulador!$D$13
Name aporte_mensal: Simulador!$D$14
Name perfil_investidor: Simulador!$D$10
Name rendimento_carteira: Simulador!$D$8
Name salario: Simulador!$D$7
Name tempo_investimento: Simulador!$D$15

Sheet Simulador
B2: Simulador de Investimentos FIIs
B6: Configurações | F6: Comparativo
B7: Salario | D7: 5000 | F7: Investimento | G7: Taxa Mensal | H7: ="Período de "&D15&" anos" -> Período de 5 anos
B8: Rendimento da Carteira | D8: 0.0108 | F8: Rendimento Carteira | G8: =D16 -> 0.0108 | H8: =FV($D$16,$D$15*12,$D$14,$D$13)*-1 -> 107498.15
B9: Investimento Sugerido (30%) | D9: =salario*30% -> 1500 | F9: Renda Fixa (CDB) | G9: 0.009 | H9: =FV($G$9,$D$15*12,$D$14,$D$13)*-1 -> 101373.22
B10: Perfil do Investidor | D10: Moderado | F10: Poupança | G10: 0.005 | H10: =FV($G$10,$D$15*12,$D$14,$D$13)*-1 -> 89259.089
B12: Simulador FIIs | F12: Tipo de Fundo | G12: Percentual Sugerido | H12: Valores
B13: Aporte Inicial | D13: 1000 | F13: Papel | G13: =VLOOKUP(perfil_investidor&"-"&F13,Chaves_Perfil_Investidor!$B$2:$E$20,4,FALSE) -> 0.32 | H13: =G13*$D$14 -> 403.2
B14: Aporte Mensal | D14: 1260 | F14: Tijolo | G14: =VLOOKUP(perfil_investidor&"-"&F14,Chaves_Perfil_Investidor!$B$2:$E$20,4,FALSE) -> 0.35 | H14: =G14*$D$14 -> 441
B15: Tempo de Investimento (Anos) | D15: 5 | F15: Híbrido | G15: =VLOOKUP(perfil_investidor&"-"&F15,Chaves_Perfil_Investidor!$B$2:$E$20,4,FALSE) -> 0.08 | H15: =G15*$D$14 -> 100.8
B16: Taxa de Rendimento Mensal | D16: =rendimento_carteira -> 0.0108 | F16: FOFs | G16: =VLOOKUP(perfil_investidor&"-"&F16,Chaves_Perfil_Investidor!$B$2:$E$20,4,FALSE) -> 0.05 | H16: =G16*$D$14 -> 63
B17: Valor Investido | D17: =aporte_inicial+(aporte_mensal*tempo_investimento*12) -> 76600 | F17: Desenvolvimento | G17: =VLOOKUP(perfil_investidor&"-"&F17,Chaves_Perfil_Investidor!$B$2:$E$20,4,FALSE) -> 0.1 | H17: =G17*$D$14 -> 126
B18: Dividendos Mensais | D18: =D19*D16 -> 1160.98 | F18: Hotelarias | G18: =VLOOKUP(perfil_investidor&"-"&F18,Chaves_Perfil_Investidor!$B$2:$E$20,4,FALSE) -> 0.1 | H18: =G18*$D$14 -> 126
B19: Total com Dividendos | D19: =FV($D$16,$D$15*12,$D$14,$D$13)*-1 -> 107498.15 | H19: =SUM(H13:H18) -> 1260
B20: Total de Dividendos | D20: =D19-D17 -> 30898.148
B22: Projeçoes Futuras | D22: Dividendos Mensais
A23: 2 | B23: 2 anos | C23: =FV($D$16,$A23*12,$D$14,$D$13)*-1 -> 35604.982 | D23: =C23*$D$16 -> 384.5338
A24: 5 | B24: 5 anos | C24: =FV($D$16,$A24*12,$D$14,$D$13)*-1 -> 107498.15 | D24: =C24*$D$16 -> 1160.98
A25: 10 | B25: 10 anos | C25: =FV($D$16,$A25*12,$D$14,$D$13)*-1 -> 310386 | D25: =C25*$D$16 -> 3352.1688
A26: 20 | B26: 20 anos | C26: =FV($D$16,$A26*12,$D$14,$D$13)*-1 -> 1433253.9 | D26: =C26*$D$16 -> 15479.142
A27: 30 | B27: 30 anos | C27: =FV($D$16,$A27*12,$D$14,$D$13)*-1 -> 5508526.2 | D27: =C27*$D$16 -> 59492.083

Sheet Chaves_Perfil_Investidor
B2: Chave | C2: Perfil | D2: Tipo de FII | E2: %
B3: =C3&"-"&D3 -> Conservador-Papel | C3: Conservador | D3: Papel | E3: 0.3
B4: =C4&"-"&D4 -> Conservador-Tijolo | C4: Conservador | D4: Tijolo | E4: 0.6
B5: =C5&"-"&D5 -> Conservador-Híbrido | C5: Conservador | D5: Híbrido | E5: 0.05
B6: =C6&"-"&D6 -> Conservador-FOFs | C6: Conservador | D6: FOFs | E6: 0.05
B7: =C7&"-"&D7 -> Conservador-Desenvolvimento | C7: Conservador | D7: Desenvolvimento | E7: 0
B8: =C8&"-"&D8 -> Conservador-Hotelarias | C8: Conservador | D8: Hotelarias | E8: 0
B9: =C9&"-"&D9 -> Moderado-Papel | C9: Moderado | D9: Papel | E9: 0.32
B10: =C10&"-"&D10 -> Moderado-Tijolo | C10: Moderado | D10: Tijolo | E10: 0.35
B11: =C11&"-"&D11 -> Moderado-Híbrido | C11: Moderado | D11: Híbrido | E11: 0.08
B12: =C12&"-"&D12 -> Moderado-FOFs | C12: Moderado | D12: FOFs | E12: 0.05
B13: =C13&"-"&D13 -> Moderado-Desenvolvimento | C13: Moderado | D13: Desenvolvimento | E13: 0.1
B14: =C14&"-"&D14 -> Moderado-Hotelarias | C14: Moderado | D14: Hotelarias | E14: 0.1
... B20: =C20&"-"&D20 -> Agressivo-Hotelarias | C20: Agressivo | D20: Hotelarias | E20: 0.1
